{
    "Home Teams": [
        {
            "Aarhus": "2.79"
        },
        {
            "Aalborg": "2.21"
        },
        {
            "FC Copenhagen": "2.14"
        },
        {
            "Randers": "2.08"
        },
        {
            "Vejle": "2.08"
        },
        {
            "Viborg": "2.00"
        },
        {
            "Nordsjaelland": "1.71"
        },
        {
            "Sonderjyske": "1.71"
        },
        {
            "Brondby": "1.57"
        },
        {
            "Midtjylland": "1.46"
        },
        {
            "Odense": "1.38"
        },
        {
            "Silkeborg": "1.31"
        }
    ],
    "Away Teams": [
        {
            "Viborg": "2.86"
        },
        {
            "Vejle": "2.79"
        },
        {
            "Aarhus": "2.38"
        },
        {
            "Aalborg": "2.31"
        },
        {
            "FC Copenhagen": "2.15"
        },
        {
            "Sonderjyske": "2.00"
        },
        {
            "Odense": "1.93"
        },
        {
            "Brondby": "1.92"
        },
        {
            "Nordsjaelland": "1.92"
        },
        {
            "Randers": "1.79"
        },
        {
            "Midtjylland": "1.71"
        },
        {
            "Silkeborg": "0.71"
        }
    ]
}