{
    "Home Teams": [
        {
            "Espanyol": "6.00"
        },
        {
            "Alaves": "5.94"
        },
        {
            "Getafe": "5.19"
        },
        {
            "Rayo Vallecano": "5.06"
        },
        {
            "Betis": "4.94"
        },
        {
            "Valencia": "4.63"
        },
        {
            "Cadiz": "4.53"
        },
        {
            "Elche": "4.50"
        },
        {
            "Levante": "4.47"
        },
        {
            "Granada": "4.19"
        },
        {
            "Sevilla": "4.06"
        },
        {
            "Villarreal": "3.94"
        },
        {
            "Osasuna": "3.82"
        },
        {
            "Real Sociedad": "3.76"
        },
        {
            "Celta Vigo": "3.47"
        },
        {
            "Mallorca": "3.47"
        },
        {
            "Real Madrid": "3.38"
        },
        {
            "Atl. Madrid": "3.29"
        },
        {
            "Ath. Bilbao": "3.00"
        },
        {
            "Barcelona": "2.00"
        }
    ],
    "Away Teams": [
        {
            "Granada": "6.76"
        },
        {
            "Alaves": "6.53"
        },
        {
            "Villarreal": "6.25"
        },
        {
            "Betis": "6.06"
        },
        {
            "Elche": "5.76"
        },
        {
            "Ath. Bilbao": "5.59"
        },
        {
            "Espanyol": "5.50"
        },
        {
            "Osasuna": "5.44"
        },
        {
            "Cadiz": "5.31"
        },
        {
            "Levante": "5.31"
        },
        {
            "Mallorca": "4.88"
        },
        {
            "Real Sociedad": "4.81"
        },
        {
            "Valencia": "4.65"
        },
        {
            "Barcelona": "4.47"
        },
        {
            "Sevilla": "4.47"
        },
        {
            "Rayo Vallecano": "4.47"
        },
        {
            "Celta Vigo": "4.44"
        },
        {
            "Getafe": "4.35"
        },
        {
            "Atl. Madrid": "4.25"
        },
        {
            "Real Madrid": "3.94"
        }
    ]
}