{
    "Home Teams": [
        {
            "Rapid Vienna": "3.33"
        },
        {
            "Admira": "2.79"
        },
        {
            "Sturm Graz": "2.67"
        },
        {
            "Salzburg": "2.36"
        },
        {
            "A. Klagenfurt": "2.27"
        },
        {
            "LASK": "2.14"
        },
        {
            "Ried": "2.13"
        },
        {
            "Hartberg": "2.07"
        },
        {
            "Wolfsberger": "2.07"
        },
        {
            "Altach": "1.93"
        },
        {
            "Tirol": "1.53"
        },
        {
            "Austria Vienna": "1.50"
        }
    ],
    "Away Teams": [
        {
            "LASK": "2.33"
        },
        {
            "Admira": "2.27"
        },
        {
            "Ried": "2.14"
        },
        {
            "Austria Vienna": "1.93"
        },
        {
            "Sturm Graz": "1.93"
        },
        {
            "Tirol": "1.93"
        },
        {
            "Altach": "1.87"
        },
        {
            "Rapid Vienna": "1.79"
        },
        {
            "Hartberg": "1.71"
        },
        {
            "Salzburg": "1.67"
        },
        {
            "Wolfsberger": "1.64"
        },
        {
            "A. Klagenfurt": "1.60"
        }
    ]
}