{
    "Home Teams": [
        {
            "PSG": "5.94"
        },
        {
            "Nantes": "5.81"
        },
        {
            "Rennes": "5.50"
        },
        {
            "Montpellier": "5.18"
        },
        {
            "Bordeaux": "5.13"
        },
        {
            "Metz": "5.06"
        },
        {
            "Strasbourg": "5.06"
        },
        {
            "Lens": "4.94"
        },
        {
            "Monaco": "4.94"
        },
        {
            "St. Etienne": "4.88"
        },
        {
            "Lorient": "4.87"
        },
        {
            "Reims": "4.73"
        },
        {
            "Troyes": "4.69"
        },
        {
            "Angers": "4.63"
        },
        {
            "Brest": "4.60"
        },
        {
            "Lyon": "4.59"
        },
        {
            "Marseille": "4.56"
        },
        {
            "Clermont": "4.50"
        },
        {
            "Lille": "4.06"
        },
        {
            "Nice": "3.88"
        }
    ],
    "Away Teams": [
        {
            "Nice": "6.00"
        },
        {
            "Metz": "5.88"
        },
        {
            "Rennes": "5.75"
        },
        {
            "Montpellier": "5.53"
        },
        {
            "Angers": "5.31"
        },
        {
            "Reims": "5.29"
        },
        {
            "Nantes": "5.25"
        },
        {
            "PSG": "5.25"
        },
        {
            "Lens": "4.88"
        },
        {
            "Lille": "4.88"
        },
        {
            "St. Etienne": "4.80"
        },
        {
            "Marseille": "4.75"
        },
        {
            "Lyon": "4.73"
        },
        {
            "Strasbourg": "4.50"
        },
        {
            "Troyes": "4.38"
        },
        {
            "Bordeaux": "4.25"
        },
        {
            "Brest": "4.24"
        },
        {
            "Clermont": "4.19"
        },
        {
            "Lorient": "4.18"
        },
        {
            "Monaco": "3.63"
        }
    ]
}